automic_rest/__init__.py
automic_rest/activatescript.py
automic_rest/branchdiff.py
automic_rest/branchlog.py
automic_rest/changeexecutionstatus.py
automic_rest/commitchanges.py
automic_rest/computeertestimations.py
automic_rest/connection.py
automic_rest/createbranch.py
automic_rest/createcomments.py
automic_rest/createforecast.py
automic_rest/createrepository.py
automic_rest/deleteclients.py
automic_rest/deleteforecast.py
automic_rest/deleterepository.py
automic_rest/executeobject.py
automic_rest/exporttelemetry.py
automic_rest/findobjects.py
automic_rest/getagentdetails.py
automic_rest/getchanges.py
automic_rest/getchildrenofexecution.py
automic_rest/getexecution.py
automic_rest/getfeaturelist.py
automic_rest/getforecast.py
automic_rest/getobjects.py
automic_rest/getrepository.py
automic_rest/gettimezoneinfo.py
automic_rest/healthcheck.py
automic_rest/help.py
automic_rest/listagentgroups.py
automic_rest/listagents.py
automic_rest/listbranches.py
automic_rest/listclients.py
automic_rest/listcomments.py
automic_rest/listexecutions.py
automic_rest/listforecastagents.py
automic_rest/listforecasts.py
automic_rest/listobjectinputs.py
automic_rest/listreportcontent.py
automic_rest/listreports.py
automic_rest/listvariables.py
automic_rest/mergebranchintoactive.py
automic_rest/modifyforecast.py
automic_rest/movehead.py
automic_rest/ping.py
automic_rest/postobjects.py
automic_rest/productlist.py
automic_rest/pullrepository.py
automic_rest/usageforcalendarevents.py
automic_rest/usageobject.py
automic_rest-0.0.6.dist-info/LICENSE
automic_rest-0.0.6.dist-info/METADATA
automic_rest-0.0.6.dist-info/WHEEL
automic_rest-0.0.6.dist-info/top_level.txt
automic_rest-0.0.6.dist-info/RECORD
