Metadata-Version: 2.1
Name: automic-rest
Version: 0.0.6
Summary: Automic REST-API
Home-page: https://github.com/ufopilot/automic_rest
Author: ufopilot
Author-email: xgadme2@gmail.com
License: UNKNOWN
Platform: UNKNOWN
Classifier: Programming Language :: Python :: 3
Classifier: License :: OSI Approved :: MIT License
Classifier: Operating System :: OS Independent
Requires-Python: >=3.6
License-File: LICENSE
Requires-Dist: requests
